digilab_beam_client/__init__.py
digilab_beam_client/_constant.py
digilab_beam_client/_evaluate.py
digilab_beam_client/_get_mesh.py
digilab_beam_client/_style_axes.py
digilab_beam_client-0.1.6.dist-info/METADATA
digilab_beam_client-0.1.6.dist-info/WHEEL
digilab_beam_client-0.1.6.dist-info/RECORD
