Metadata-Version: 2.1
Name: digilab-beam-client
Version: 0.1.6
Summary: 
Author: JWSchaefer
Author-email: joe.w.schaefer@gmail.com
Requires-Python: >=3.10,<3.13
Classifier: Programming Language :: Python :: 3
Classifier: Programming Language :: Python :: 3.10
Classifier: Programming Language :: Python :: 3.11
Classifier: Programming Language :: Python :: 3.12
Requires-Dist: numpy (>=1.26)
Requires-Dist: requests (>=2.32.3,<3.0.0)
Requires-Dist: typeguard (>=4.3.0,<5.0.0)
